odoo/addons/website_sale_show_company_data/README.rst
odoo/addons/website_sale_show_company_data/__init__.py
odoo/addons/website_sale_show_company_data/__manifest__.py
odoo/addons/website_sale_show_company_data/i18n/ca.po
odoo/addons/website_sale_show_company_data/i18n/es.po
odoo/addons/website_sale_show_company_data/i18n/fr.po
odoo/addons/website_sale_show_company_data/i18n/it.po
odoo/addons/website_sale_show_company_data/i18n/website_sale_show_company_data.pot
odoo/addons/website_sale_show_company_data/readme/CONFIGURATION.rst
odoo/addons/website_sale_show_company_data/readme/CONTRIBUTORS.rst
odoo/addons/website_sale_show_company_data/readme/DESCRIPTION.rst
odoo/addons/website_sale_show_company_data/readme/USAGE.rst
odoo/addons/website_sale_show_company_data/static/description/icon.png
odoo/addons/website_sale_show_company_data/static/description/index.html
odoo/addons/website_sale_show_company_data/views/website_sale_address.xml
odoo14_addon_website_sale_show_company_data-14.0.1.0.1.dev5.dist-info/METADATA
odoo14_addon_website_sale_show_company_data-14.0.1.0.1.dev5.dist-info/WHEEL
odoo14_addon_website_sale_show_company_data-14.0.1.0.1.dev5.dist-info/top_level.txt
odoo14_addon_website_sale_show_company_data-14.0.1.0.1.dev5.dist-info/RECORD
